flet_sqlite3/__init__.py
flet_sqlite3/database.db
flet_sqlite3/database.py
flet_sqlite3/main.py
flet_sqlite3-0.5.0.dist-info/licenses/LICENSE
flet_sqlite3-0.5.0.dist-info/METADATA
flet_sqlite3-0.5.0.dist-info/WHEEL
flet_sqlite3-0.5.0.dist-info/top_level.txt
flet_sqlite3-0.5.0.dist-info/RECORD
