Metadata-Version: 2.4
Name: flet_sqlite3
Version: 0.5.0
Summary: Приложение для учета партнеров и расчета скидок с использованием Flet и SQLite3
Home-page: https://github.com/noon/flet_sqlite3
Author: Noon
Author-email: noon@example.com
Classifier: Programming Language :: Python :: 3
Classifier: License :: OSI Approved :: MIT License
Classifier: Operating System :: OS Independent
Requires-Python: >=3.6
License-File: LICENSE
Requires-Dist: flet>=0.28.0
Requires-Dist: openpyxl>=3.1.0
Dynamic: author
Dynamic: author-email
Dynamic: classifier
Dynamic: description
Dynamic: description-content-type
Dynamic: home-page
Dynamic: license-file
Dynamic: requires-dist
Dynamic: requires-python
Dynamic: summary
